Workbook

Sheet Temperature
A1: Factors | B1: Iran | E1: Canada | N1: Norway | T1: England | Z1: Switzerland | AC1: Denmark
B2: Tehran | E2: Vancouver | H2: Toronto | K2: Calgary | N2: Oslo | Q2: Bergen | T2: London | W2: Birmingham | Z2: Zurich | AC2: Copenhagen
A3: height from sea level(Meter) | B3: 1200 | E3: 2 | H3: 76 | K3: 1045 | N3: 23 | Q3: 0 | T3: 11 | W3: 140 | Z3: 408 | AC3: 40
A4: Feels like
A5: Humidity(%) | B5: 40(60-20) | E5: 70(80-60) | H5: 81(86-76) | K5: 60(72-48) | N5: 74(83-60) | Q5: 78(80-75) | T5: 73(83-64) | W5: 70(78-65) | Z5: 79(84-76) | AC5: 79(88-68)
A6: Pressure(MB) | B6: 1015 | E6: 1015 | H6: 1015 | K6: 1020 | N6: 1013 | Q6: 1010 | T6: 1012 | W6: 1020 | Z6: 1018 | AC6: 1007
A7: most coldest record | B7: -15 | E7: -23 | H7: -33 | K7: -43 | N7: -29 | Q7: -19.5 | T7: -3 | W7: -6 | Z7: -5 | AC7: -8
A8: most warmest record | B8: 43 | E8: 34 | H8: 40 | K8: 36 | N8: 35 | Q8: 33 | T8: 38 | W8: 42 | Z8: 38 | AC8: 32
A9: yearly average per month | B9: Rain(days) | C9: Low | D9: High | E9: Rain(days) | F9: Low | G9: High | H9: Rain(days) | I9: Low | J9: High | K9: Rain(days) | L9: Low | M9: High | N9: Rain(days) | O9: Low | P9: High | Q9: Rain(days) | R9: Low | S9: High | T9: Rain(days) | U9: Low | V9: High | W9: Rain(days) | X9: Low | Y9: High | Z9: Rain(days) | AA9: Low | AB9: High | AC9: Rain(days) | AD9: Low | AE9: High
A10: January | B10: 4 | C10: 0 | D10: 8 | E10: 12 | F10: 2 | G10: 7 | H10: 9 | I10: -7 | J10: 0 | K10: 4 | L10: -11 | M10: 0 | N10: 9 | O10: -5 | P10: 0 | Q10: 18 | R10: 0 | S10: 4 | T10: 8 | U10: 2 | V10: 7 | W10: 8 | X10: 1 | Y10: 12 | Z10: 10 | AA10: -2 | AB10: 3 | AC10: 9 | AD10: -2 | AE10: 2
A11: February | B11: 4 | C11: 2 | D11: 11 | E11: 12 | F11: 1 | G11: 7 | H11: 7 | I11: -6 | J11: 0 | K11: 3 | L11: -13 | M11: -2 | N11: 7 | O11: -5 | P11: 0 | Q11: 16 | R11: -1 | S11: 4 | T11: 7 | U11: 2 | V11: 7 | W11: 7 | X11: 4 | Y11: 15 | Z11: 9 | AA11: -2 | AB11: 5 | AC11: 7 | AD11: -3 | AE11: 4
A12: March | B12: 4 | C12: 7 | D12: 16 | E12: 10 | F12: 4 | G12: 10 | H12: 8 | I12: -2 | J12: 5 | K12: 4 | L12: -7 | M12: 4 | N12: 7 | O12: -2 | P12: 4 | Q12: 16 | R12: 1 | S12: 6 | T12: 8 | U12: 3 | V12: 10 | W12: 8 | X12: 7 | Y12: 19 | Z12: 10 | AA12: 2 | AB12: 10 | AC12: 8 | AD12: 0 | AE12: 5
A13: April | B13: 4 | C13: 12 | D13: 22 | E13: 8 | F13: 6 | G13: 13 | H13: 8 | I13: 3 | J13: 12 | K13: 5 | L13: -2 | M13: 10 | N13: 7 | O13: 2 | P13: 10 | Q13: 13 | R13: 3 | S13: 9 | T13: 9 | U13: 4 | V13: 13 | W13: 7 | X13: 12 | Y13: 25 | Z13: 11 | AA13: 4 | AB13: 14 | AC13: 7 | AD13: 2 | AE13: 10
A14: May | B14: 2 | C14: 17 | D14: 28 | E14: 6 | F14: 9 | G14: 17 | H14: 8 | I14: 11 | J14: 20 | K14: 7 | L14: 4 | M14: 17 | N14: 8 | O14: 7 | P14: 16 | Q14: 12 | R14: 7 | S14: 14 | T14: 8 | U14: 8 | V14: 16 | W14: 7 | X14: 17 | Y14: 28 | Z14: 12 | AA14: 9 | AB14: 18 | AC14: 8 | AD14: 7 | AE14: 16
A15: June | B15: 0 | C15: 22 | D15: 34 | E15: 6 | F15: 12 | G15: 20 | H15: 7 | I15: 15 | J15: 24 | K15: 8 | L15: 8 | M15: 20 | N15: 9 | O15: 11 | P15: 20 | Q15: 12 | R15: 10 | S15: 17 | T15: 7 | U15: 11 | V15: 19 | W15: 7 | X15: 21 | Y15: 32 | Z15: 12 | AA15: 12 | AB15: 22 | AC15: 8 | AD15: 11 | AE15: 19
A16: July | B16: 0 | C16: 25 | D16: 37 | E16: 4 | F16: 14 | G16: 23 | H16: 7 | I16: 18 | J16: 28 | K16: 8 | L16: 11 | M16: 24 | N16: 10 | O16: 13 | P16: 22 | Q16: 14 | R16: 12 | S16: 18 | T16: 8 | U16: 13 | V16: 21 | W16: 9 | X16: 23 | Y16: 33 | Z16: 11 | AA16: 14 | AB16: 24 | AC16: 9 | AD16: 13 | AE16: 21
A17: August | B17: 0 | C17: 24 | D17: 36 | E17: 4 | F17: 14 | G17: 23 | H17: 7 | I17: 18 | J17: 26 | K17: 6 | L17: 10 | M17: 23 | N17: 10 | O17: 12 | P17: 21 | Q17: 16 | R17: 12 | S17: 17 | T17: 8 | U17: 13 | V17: 21 | W17: 7 | X17: 22 | Y17: 33 | Z17: 11 | AA17: 14 | AB17: 23 | AC17: 10 | AD17: 12 | AE17: 21
A18: September | B18: 0 | C18: 20 | D18: 32 | E18: 5 | F18: 12 | G18: 19 | H18: 7 | I18: 14 | J18: 22 | K18: 6 | L18: 5 | M18: 18 | N18: 9 | O18: 8 | P18: 16 | Q18: 17 | R18: 9 | S18: 14 | T18: 7 | U18: 11 | V18: 18 | W18: 6 | X18: 19 | Y18: 31 | Z18: 9 | AA18: 10 | AB18: 19 | AC18: 8 | AD18: 10 | AE18: 17
A19: October | B19: 1 | C19: 14 | D19: 25 | E19: 9 | F19: 7 | G19: 14 | H19: 7 | I19: 8 | J19: 15 | K19: 3 | L19: -1 | M19: 11 | N19: 10 | O19: 4 | P19: 9 | Q19: 19 | R19: 7 | S19: 11 | T19: 8 | U19: 8 | V19: 14 | W19: 6 | X19: 12 | Y19: 25 | Z19: 9 | AA19: 7 | AB19: 14 | AC19: 9 | AD19: 7 | AE19: 12
A20: November | B20: 4 | C20: 7 | D20: 16 | E20: 13 | F20: 3 | G20: 9 | H20: 8 | I20: 2 | J20: 8 | K20: 3 | L20: -8 | M20: 3 | N20: 10 | O20: -1 | P20: 4 | Q20: 17 | R20: 3 | S20: 7 | T20: 8 | U20: 4 | V20: 10 | W20: 8 | X20: 6 | Y20: 18 | Z20: 10 | AA20: 2 | AB20: 7 | AC20: 9 | AD20: 3 | AE20: 7
A21: December | B21: 3 | C21: 8 | D21: 10 | E21: 12 | F21: 1 | G21: 6 | H21: 9 | I21: -3 | J21: 3 | K21: 3 | L21: -12 | M21: -1 | N21: 8 | O21: -5 | P21: 0 | Q21: 19 | R21: 1 | S21: 5 | T21: 8 | U21: 2 | V21: 7 | W21: 7 | X21: 4 | Y21: 14 | Z21: 10 | AA21: -1 | AB21: 4 | AC21: 9 | AD21: 0 | AE21: 4
A22: average temperature per year | B22: =(B10+B11+B12+B13+B14+B15+B16+B17+B18+B19+B20+B21)/12 -> 2.1666667 | C22: =(C10+C11+C12+C13+C14+C15+C16+C17+C18+C19+C20+C21)/12 -> 13.166667 | D22: =(D10+D11+D12+D13+D14+D15+D16+D17+D18+D19+D20+D21)/12 -> 22.916667 | E22: =(E10+E11+E12+E13+E14+E15+E16+E17+E18+E19+E20+E21)/12 -> 8.4166667 | F22: =(F10+F11+F12+F13+F14+F15+F16+F17+F18+F19+F20+F21)/12 -> 7.0833333 | G22: =(G10+G11+G12+G13+G14+G15+G16+G17+G18+G19+G20+G21)/12 -> 14 | H22: =(H10+H11+H12+H13+H14+H15+H16+H17+H18+H19+H20+H21)/12 -> 7.6666667 | I22: =(I10+I11+I12+I13+I14+I15+I16+I17+I18+I19+I20+I21)/12 -> 5.9166667 | ... AE22: =(AE10+AE11+AE12+AE13+AE14+AE15+AE16+AE17+AE18+AE19+AE20+AE21)/12 -> 11.5

Sheet Living Costs
A1: Factors | B1: Iran | C1: Canada | F1: Norway | H1: England | J1: switzerland | K1: Denmark
B2: Tehran | C2: Vancouver | D2: Toronto | E2: Calgary | F2: Oslo | G2: Bergen | H2: London | I2: Birmingham | J2: Zurich | K2: Copenhagen
A3: هزینه خانواده 4 نفره بدون اجاره | B3: 1365.49 | C3: 3536.96 | D3: 3520.01 | E3: 3397.28 | F3: 4561.3 | G3: 4472.29 | H3: 4119.37 | I3: 2973.95 | J3: 6300.95 | K3: 4135.91
A4: هزینه فرد مجرد بدون اجاره | B4: 377.22 | C4: 961.24 | D4: 970.72 | E4: 954.12 | F4: 1246.67 | G4: 1240.98 | H4: 1169.92 | I4: 851.16 | J4: 1706.17 | K4: 1139.56
A5: Resturants
A6: Meal, Inexpensive Restaurant | B6: 3.5 | C6: 15.9 | D6: 15.9 | E6: 15.9 | F6: 21.32 | G6: 21.32 | H6: 20.33 | I6: 13.56 | J6: 27.42 | K6: 20
A7: Meal for 2 People, Mid-range Restaurant, Three-course | B7: 32.94 | C7: 63.59 | D7: 63.59 | E7: 63.59 | F7: 109.42 | G7: 89.78 | H7: 81.34 | I7: 67.78 | J7: 131.62 | K7: 107.66
A8: McMeal at McDonalds (or Equivalent Combo Meal) | B8: 3 | C8: 9.54 | D8: 9.54 | E8: 8.37 | F8: 12.34 | G8: 12.91 | H8: 8.13 | I8: 6.78 | J8: 16.45 | K8: 12
A9: Domestic Non-Alcoholic Beer (0.5 liter draught) | B9: 0.8 | C9: 5.56 | D9: 5.56 | E9: 5.56 | F9: 10.1 | G9: 10.1 | H9: 6.78 | I9: 5.42 | J9: 7.68 | K9: 7.69
A10: Imported Non-Alcoholic Beer (0.33 liter bottle) | B10: 1.5 | C10: 6.36 | D10: 7.15 | E10: 5.96 | F10: 10.1 | G10: 7.86 | H10: 6.78 | I10: 5.42 | J10: 7.68 | K10: 6.92
A11: Cappuccino (regular) | B11: 1.26 | C11: 3.95 | D11: 3.81 | E11: 3.48 | F11: 4.93 | G11: 5.08 | H11: 4.19 | I11: 3.73 | J11: 5.48 | K11: 6.12
A12: Coke/Pepsi (0.33 liter bottle) | B12: 0.86 | C12: 1.97 | D12: 1.93 | E12: 1.62 | F12: 3.54 | G12: 2.97 | H12: 1.99 | I12: 1.8 | J12: 4.92 | K12: 3.65
A13: Water (0.33 liter bottle) | B13: 0.65 | C13: 1.75 | D13: 1.46 | E13: 1.3 | F13: 3.22 | G13: 2.42 | H13: 1.62 | I13: 1.4 | J13: 4.55 | K13: 2.94
A14: Markets
A15: Milk (regular), (1 liter) | B15: 0.74 | C15: 1.76 | D15: 2.22 | E15: 1.47 | F15: 2.13 | G15: 2.09 | H15: 1.26 | I15: 1.22 | J15: 1.85 | K15: 1.64
A16: Loaf of Fresh White Bread (500g) | B16: 0.42 | C16: 2.65 | D16: 2.3 | E16: 1.94 | F16: 3.05 | G16: 3.36 | H16: 1.49 | I16: 1.27 | J16: 3.05 | K16: 3.17
A17: Rice (white), (1kg) | B17: 1.73 | C17: 3.26 | D17: 2.49 | E17: 2.26 | F17: 3.51 | G17: 1.92 | H17: 2.27 | I17: 1.77 | J17: 3.09 | K17: 2.4
A18: Eggs (regular) (12) | B18: 1.31 | C18: 3.75 | D18: 2.82 | E18: 2.86 | F18: 4.27 | G18: 4.53 | H18: 3.04 | I18: 2.45 | J18: 7.21 | K18: 4.14
A19: Local Cheese (1kg) | B19: 3.3 | C19: 12.27 | D19: 12.48 | E19: 11.02 | F19: 11.89 | G19: 12.67 | H19: 8.44 | I19: 8.67 | J19: 28.56 | K19: 13.52
A20: Chicken Fillets (1kg) | B20: 2.85 | C20: 12.39 | D20: 10.73 | E20: 10.9 | F20: 15.44 | G20: 13.64 | H20: 7.69 | I20: 6.89 | J20: 31.15 | K20: 9.33
A21: Beef Round (1kg) (or Equivalent Back Leg Red Meat) | B21: 7.03 | C21: 16.28 | D21: 12.77 | E21: 12.17 | F21: 28.06 | G21: 29.31 | H21: 14.78 | I21: 10.46 | J21: 56.09 | K21: 15.27
A22: Apples (1kg) | B22: 0.95 | C22: 3.09 | D22: 2.98 | E22: 3.58 | F22: 3.32 | G22: 3.39 | H22: 2.78 | I22: 2.51 | J22: 4.22 | K22: 3.07
A23: Banana (1kg) | B23: 1.21 | C23: 1.46 | D23: 1.26 | E23: 1.48 | F23: 2.39 | G23: 2.46 | H23: 1.36 | I23: 1.31 | J23: 3.08 | K23: 2.86
A24: Oranges (1kg) | B24: 0.9 | C24: 3.15 | D24: 2.83 | E24: 3.28 | F24: 3.23 | G24: 3.1 | H24: 2.38 | I24: 2.36 | J24: 3.51 | K24: 2.96
A25: Tomato (1kg) | B25: 0.53 | C25: 3.65 | D25: 3.01 | E25: 3.9 | F25: 4.03 | G25: 4.06 | H25: 3.15 | I25: 2.55 | J25: 4.64 | K25: 4.41
A26: Potato (1kg) | B26: 0.41 | C26: 2.19 | D26: 2.13 | E26: 1.95 | F26: 2.39 | G26: 2.33 | H26: 1.41 | I26: 1.47 | J26: 2.43 | K26: 1.93
... A33: Cigarettes 20 Pack (Marlboro) | B33: 2.2 | C33: 14.31 | D33: 13.51 | E33: 13.12 | F33: 15.65 | G33: 14.59 | H33: 17.01 | I33: 14.91 | J33: 9.6 | K33: 8.57
A34: Transportation
A35: One-way Ticket (Local Transport) | B35: 0.36 | C35: 2.42 | D35: 2.58 | E35: 2.78 | F35: 4.26 | G35: 4.38 | H35: 3.52 | I35: 3.25 | J35: 4.39 | K35: 3.69
A36: Monthly Pass (Regular Price) | B36: 11.88 | C36: 95.39 | D36: 124.01 | E36: 86.65 | F36: 89.22 | G36: 89.78 | H36: 214.19 | I36: 88.8 | J36: 93.23 | K36: 86.13
A37: Taxi Start (Normal Tariff) | B37: 0.48 | C37: 2.98 | D37: 3.38 | E37: 3.02 | F37: 11.22 | G37: 10.1 | H37: 4.07 | I37: 2.98 | J37: 6.58 | K37: 6.92
A38: Taxi 1km (Normal Tariff) | B38: 0.4 | C38: 1.49 | D38: 1.59 | E38: 1.59 | F38: 1.57 | G38: 1.35 | H38: 2.3 | I38: 1.52 | J38: 4.17 | K38: 2
A39: Taxi 1hour Waiting (Normal Tariff) | B39: 3.57 | C39: 27.82 | D39: 27.82 | E39: 26.87 | F39: 54.99 | G39: 80.8 | H39: 39.04 | I39: 21.15 | J39: 75.68 | K39: 63.84
A40: Gasoline (1 liter) | B40: 0.64 | C40: 1.29 | D40: 1.1 | E40: 1.06 | F40: 1.94 | G40: 1.93 | H40: 1.92 | I40: 1.86 | J40: 1.83 | K40: 1.84
A41: Volkswagen Golf 1.4 90 KW Trendline (Or Equivalent New Car) | B41: 50000 | C41: 20667.73 | D41: 20667.73 | E41: 22257.55 | F41: 39277.74 | G41: 33666.63 | H41: 31798.78 | I41: 33891.23 | J41: 32603.57 | K41: 39987.7
A42: Toyota Corolla Sedan 1.6l 97kW Comfort (Or Equivalent New Car) | B42: 52448.27 | C42: 19357.75 | D42: 20050.75 | E42: 19330.41 | F42: 37299.43 | G42: 37818.43 | H42: 32169.64 | I42: 29382.51 | J42: 31520.44 | K42: 39495.54
A43: Utilities (Monthly)
A44: Basic (Electricity, Heating, Cooling, Water, Garbage) for 85m2 Apartment | B44: 31.05 | C44: 75.24 | D44: 126.11 | E44: 158.03 | F44: 159.88 | G44: 204.99 | H44: 270.74 | I44: 196.09 | J44: 231.78 | K44: 183.95
A45: 1 min. of Prepaid Mobile Tariff Local (No Discounts or Plans) | B45: 0.01 | C45: 0.27 | D45: 0.3 | E45: 0.22 | F45: 0.15 | G45: 0.1 | H45: 0.18 | I45: 0.12 | J45: 0.3 | K45: 0.18
A46: Internet (60 Mbps or More, Unlimited Data, Cable/ADSL) | B46: 16.34 | C46: 68.12 | D46: 58.33 | E46: 70.38 | F46: 52.88 | G46: 56.2 | H46: 43.16 | I46: 36.56 | J46: 57.37 | K46: 38.97
A47: Sports And Leisure
A48: Fitness Club, Monthly Fee for 1 Adult | B48: 25.74 | C48: 44.64 | D48: 48.4 | E48: 55.54 | F48: 51.43 | G48: 49.82 | H48: 61.63 | I48: 33.27 | J48: 97.16 | K48: 42.62
A49: Tennis Court Rent (1 Hour on Weekend) | B49: 13.42 | C49: 12.37 | D49: 18.86 | E49: 17.86 | F49: 35.44 | G49: 34.25 | H49: 14.28 | I49: 17.28 | J49: 38.26 | K49: 32.3
A50: Cinema, International Release, 1 Seat | B50: 3.56 | C50: 11.92 | D50: 11.92 | E50: 11.92 | F50: 15.71 | G50: 16.83 | H50: 19.62 | I50: 12.2 | J50: 21.39 | K50: 18.07
A51: Childcare
A52: Preschool (or Kindergarten), Full Day, Private, Monthly for 1 Child | B52: 111.37 | C52: 1032.52 | D52: 1350.21 | E52: 970.17 | F52: 362.42 | G52: 364.39 | H52: 1941.53 | I52: 1152.3 | J52: 2943.92 | K52: 495.07
A53: International Primary School, Yearly for 1 Child | B53: 1904.82 | C53: 25935.04 | D53: 20096.38 | E53: 12817.97 | F53: 11398.56 | G53: 5436.71 | H53: 24207.18 | I53: 18753.15 | J53: 32972.7 | K53: 9489.39
A54: Clothing And Shoes
A55: 1 Pair of Jeans (Levis 501 Or Similar) | B55: 50.84 | C55: 63.85 | D55: 58.14 | E55: 49.39 | F55: 102.93 | G55: 99.86 | H55: 79.11 | I55: 83.15 | J55: 109.19 | K55: 115.86
A56: 1 Summer Dress in a Chain Store (Zara, H&M, ...) | B56: 39.69 | C56: 39.2 | D56: 37.91 | E56: 43.22 | F56: 44.88 | G56: 42.48 | H56: 41.07 | I56: 37.02 | J56: 51.84 | K56: 51.3
A57: 1 Pair of Nike Running Shoes (Mid-Range) | B57: 153.18 | C57: 91.65 | D57: 88.57 | E57: 79.52 | F57: 103.46 | G57: 120.95 | H57: 99.88 | I57: 91.93 | J57: 118.42 | K57: 124.9
A58: 1 Pair of Men Leather Business Shoes | B58: 90.55 | C58: 128.4 | D58: 111.22 | E58: 98.09 | F58: 130.27 | G58: 149.62 | H58: 121.16 | I58: 80.37 | J58: 202.58 | K58: 184.43
A59: Rent Per Month
A60: Apartment (1 bedroom) in City Centre | B60: 533.39 | C60: 1681.7 | D60: 1609 | E60: 1031.77 | F60: 1545.26 | G60: 1122.22 | H60: 2353.41 | I60: 1026.23 | J60: 2172.21 | K60: 1671.2
A61: Apartment (1 bedroom) Outside of Centre | B61: 446.99 | C61: 1345.07 | D61: 1363.45 | E61: 860.33 | F61: 1206.24 | G61: 850.3 | H61: 1752.7 | I61: 794.12 | J61: 1583.53 | K61: 1268.36
A62: Apartment (3 bedrooms) in City Centre | B62: 1464.93 | C62: 3261.63 | D62: 2795.69 | E62: 1889.45 | F62: 2412.85 | G62: 1761.89 | H62: 4708.13 | I62: 1979.9 | J62: 4090.57 | K62: 2588.21
A63: Apartment (3 bedrooms) Outside of Centre | B63: 1004.51 | C63: 2352.51 | D63: 2199.03 | E63: 1446 | F63: 1910.31 | G63: 1561.8 | H63: 2914.34 | I63: 1273.51 | J63: 2875.98 | K63: 2123.74
A64: Buy Apartment Price
A65: Price per Square Meter to Buy Apartment in City Centre | B65: 2688.04 | C65: 9376.46 | D65: 8981.17 | E65: 3111.05 | F65: 10070.81 | G65: 6102.08 | H65: 16672.55 | I65: 4892.58 | J65: 14878.57 | K65: 8204.62
A66: Price per Square Meter to Buy Apartment Outside of Centre | B66: 1373.5 | C66: 7140.21 | D66: 7286.93 | E66: 2309.04 | F66: 6557.51 | G66: 3997.91 | H66: 8022.86 | I66: 2787.47 | J66: 10177.53 | K66: 5735.08
A67: Salaries And Financing
A68: Average Monthly Net Salary (After Tax) | B68: 237.87 | C68: 3488.91 | D68: 3848.1 | E68: 3701.98 | F68: 3789.47 | G68: 3540.42 | H68: 4277.27 | I68: 2469.91 | J68: 7952.31 | K68: 3784.29
A69: Mortgage Interest Rate in Percentages (%), Yearly, for 20 Years Fixed-Rate | B69: 20.59 | C69: 2.31 | D69: 2.47 | E69: 2.49 | F69: 2.29 | G69: 2.42 | H69: 2.55 | I69: 2.95 | J69: 1.21 | K69: 1.34
A70: در 12 ماه گذشته چند نفر این اطلاعات را پر کرده اند | B70: 341 | C70: 381 | D70: 678 | E70: 249 | F70: 169 | G70: 33 | H70: 753 | I70: 72 | J70: 230 | K70: 216
A72: Results for us
A73: زندگی برای دو نفر بدون اجاره | B73: =B3/2 -> 682.745 | C73: =C3/2 -> 1768.48 | D73: =D3/2 -> 1760.005 | E73: =E3/2 -> 1698.64 | F73: =F3/2 -> 2280.65 | G73: =G3/2 -> 2236.145 | H73: =H3/2 -> 2059.685 | I73: =I3/2 -> 1486.975 | ... K73: =K3/2 -> 2067.955
A74: زندگی برای دو نفر با اجاره خانه یک خوابه در مرکز شهر | B74: =B73+B60 -> 1216.135 | C74: =C73+C60 -> 3450.18 | D74: =D73+D60 -> 3369.005 | E74: =E73+E60 -> 2730.41 | F74: =F73+F60 -> 3825.91 | G74: =G73+G60 -> 3358.365 | H74: =H73+H60 -> 4413.095 | I74: =I73+I60 -> 2513.205 | ... K74: =K73+K60 -> 3739.155
A75: درآمد خالص میانگین یک نفر بعد از مالیات - (منهایی) هزینه های زندگی برای دو نفر با خانه یک خوابه در مرکز شهر | B75: =B68-B74 -> -978.265 | C75: =C68-C74 -> 38.73 | D75: =D68-D74 -> 479.095 | E75: =E68-E74 -> 971.57 | F75: =F68-F74 -> -36.44 | G75: =G68-G74 -> 182.055 | H75: =H68-H74 -> -135.825 | I75: =I68-I74 -> -43.295 | ... K75: =K68-K74 -> 45.135
A76: بدترین حالت حقوق
A77: آیدین
A78: حقوق سالانه | C78: =(100% - Tax!J11) * ('Works and Salarys'!C6) -> 43438.049 | D78: =(100% - Tax!J18) * ('Works and Salarys'!D6) -> 40191.111 | E78: =(100% - Tax!J22) * ('Works and Salarys'!E6) -> 39205.645 | F78: =(100% - Tax!J30) * ('Works and Salarys'!F6) -> 47560.458 | G78: =(100% - Tax!J29) * ('Works and Salarys'!G6) -> 48218.4 | H78: =(100% - Tax!J34) * ('Works and Salarys'!H6) -> 43010.4 | I78: =(100% - Tax!J34) * ('Works and Salarys'!I6) -> 37918.4 | J78: =(100% - Tax!J41) * ('Works and Salarys'!J6) -> 79763.52 | K78: =(100% - Tax!J53) * ('Works and Salarys'!K6) -> 44498.27
A79: حقوق ماهانه | C79: =C78/12 -> 3619.8374 | D79: =D78/12 -> 3349.2592 | E79: =E78/12 -> 3267.1371 | F79: =F78/12 -> 3963.3715 | G79: =G78/12 -> 4018.2 | H79: =H78/12 -> 3584.2 | I79: =I78/12 -> 3159.8667 | J79: =J78/12 -> 6646.96 | K79: =K78/12 -> 3708.1891
A80: بشارت
A81: حقوق سالانه | C81: =(100% - Tax!J11) * ('Works and Salarys'!C14) -> 32849.712 | D81: =(100% - Tax!J18) * ('Works and Salarys'!D14) -> 31558.732 | E81: =(100% - Tax!J22) * ('Works and Salarys'!E14) -> 30019.135 | F81: =(100% - Tax!J29) * ('Works and Salarys'!F14) -> 40796.94 | G81: =(100% - Tax!J29) * ('Works and Salarys'!G14) -> 36815.74 | H81: =(100% - Tax!J34) * ('Works and Salarys'!H14) -> 43597.6 | I81: =(100% - Tax!J34) * ('Works and Salarys'!I14) -> 32120 | J81: =(100% - Tax!J40) * ('Works and Salarys'!J14) -> 69566.46 | K81: =(100% - Tax!J53) * ('Works and Salarys'!K14) -> 39558.21
A82: حقوق ماهانه | C82: =C81/12 -> 2737.476 | D82: =D81/12 -> 2629.8943 | E82: =E81/12 -> 2501.5946 | F82: =F81/12 -> 3399.745 | G82: =G81/12 -> 3067.9783 | H82: =H81/12 -> 3633.1333 | I82: =I81/12 -> 2676.6667 | J82: =J81/12 -> 5797.205 | K82: =K81/12 -> 3296.5175
A83: جمع ما
A84: جمع کل بدترین حالت در ماه بعد از مالیات | C84: =C79+C82 -> 6357.3134 | D84: =D79+D82 -> 5979.1536 | E84: =E79+E82 -> 5768.7317 | F84: =F79+F82 -> 7363.1165 | G84: =G79+G82 -> 7086.1783 | H84: =H79+H82 -> 7217.3333 | I84: =I79+I82 -> 5836.5333 | J84: =J79+J82 -> 12444.165 | K84: =K79+K82 -> 7004.7066
A85: جمع کل بدترین حالت در سال بعد از مالیات | C85: =C78+C81 -> 76287.761 | D85: =D78+D81 -> 71749.843 | E85: =E78+E81 -> 69224.78 | F85: =F78+F81 -> 88357.398 | G85: =G78+G81 -> 85034.14 | H85: =H78+H81 -> 86608 | I85: =I78+I81 -> 70038.4 | J85: =J78+J81 -> 149329.98 | K85: =K78+K81 -> 84056.479
A86: خالص باقی مانده بعد از هزینه های جاری زندگی در هر ماه | C86: =C84-C74 -> 2907.1334 | D86: =D84-D74 -> 2610.1486 | E86: =E84-E74 -> 3038.3217 | F86: =F84-F74 -> 3537.2065 | G86: =G84-G74 -> 3727.8133 | H86: =H84-H74 -> 2804.2383 | I86: =I84-I74 -> 3323.3283 | J86: =J84-J74 -> 7121.48 | K86: =K84-K74 -> 3265.5516
A87: جمع باقی مانده خالص بعد از هزینه های جاری برای یک سال | C87: =C86*12 -> 34885.601 | D87: =D86*12 -> 31321.783 | E87: =E86*12 -> 36459.86 | F87: =F86*12 -> 42446.478 | G87: =G86*12 -> 44733.76 | H87: =H86*12 -> 33650.86 | I87: =I86*12 -> 39879.94 | J87: =J86*12 -> 85457.76 | K87: =K86*12 -> 39186.619
A88: میانگین حالت حقوق
A89: آیدین
A90: حقوق سالانه | C90: =(100% - Tax!J14) * ('Works and Salarys'!C4) -> 62486.424 | D90: =(100% - Tax!J20) * ('Works and Salarys'!D4) -> 66938.647 | E90: =(100% - Tax!J23) * ('Works and Salarys'!E4) -> 65373.88 | F90: =(100% -Tax!J30) * ('Works and Salarys'!F4) -> 67266.688 | G90: =(100% -Tax!J30) * ('Works and Salarys'!G4) -> 59535.36 | H90: =(100% - Tax!J35) * ('Works and Salarys'!H4) -> 62078.4 | I90: =(100% - Tax!J35) * ('Works and Salarys'!I4) -> 44689.8 | J90: =(100% -Tax!J43) * ('Works and Salarys'!J4) -> 110771.48 | K90: =(100% - Tax!J54) * ('Works and Salarys'!K4) -> 47819.422
A91: حقوق ماهانه | C91: =C90/12 -> 5207.202 | D91: =D90/12 -> 5578.2206 | E91: =E90/12 -> 5447.8233 | F91: =F90/12 -> 5605.5573 | G91: =G90/12 -> 4961.28 | H91: =H90/12 -> 5173.2 | I91: =I90/12 -> 3724.15 | J91: =J90/12 -> 9230.9567 | K91: =K90/12 -> 3984.9518
A92: بشارت
A93: حقوق سالانه | C93: =(100% - Tax!J11) * ('Works and Salarys'!C12) -> 45225.012 | D93: =(100% - Tax!J18) * ('Works and Salarys'!D12) -> 43446.985 | E93: =(100% - Tax!J22) * ('Works and Salarys'!E12) -> 41327.48 | F93: =(100% - Tax!J30) * ('Works and Salarys'!F12) -> 49030.754 | G93: =(100% - Tax!J29) * ('Works and Salarys'!G12) -> 50684.08 | H93: =(100% - Tax!J35) * ('Works and Salarys'!H12) -> 45016.8 | I93: =(100% - Tax!J34) * ('Works and Salarys'!I12) -> 44221.6 | J93: =(100% -Tax!J42) * ('Works and Salarys'!J12) -> 94060.45 | K93: =(100% - Tax!J54) * ('Works and Salarys'!K12) -> 41379.296
A94: حقوق ماهانه | C94: =C93/12 -> 3768.751 | D94: =D93/12 -> 3620.5821 | E94: =E93/12 -> 3443.9567 | F94: =F93/12 -> 4085.8962 | G94: =G93/12 -> 4223.6733 | H94: =H93/12 -> 3751.4 | I94: =I93/12 -> 3685.1333 | J94: =J93/12 -> 7838.3708 | K94: =K93/12 -> 3448.2747
A95: جمع ما
A96: جمع کل میانگین حالت در ماه بعد از مالیات | C96: =C91+C94 -> 8975.953 | D96: =D91+D94 -> 9198.8027 | E96: =E91+E94 -> 8891.78 | F96: =F91+F94 -> 9691.4535 | G96: =G91+G94 -> 9184.9533 | H96: =H91+H94 -> 8924.6 | I96: =I91+I94 -> 7409.2833 | J96: =J91+J94 -> 17069.327 | K96: =K91+K94 -> 7433.2265
A97: جمع کل میانگین حالت در سال بعد از مالیات | C97: =C90+C93 -> 107711.44 | D97: =D90+D93 -> 110385.63 | E97: =E90+E93 -> 106701.36 | F97: =F90+F93 -> 116297.44 | G97: =G90+G93 -> 110219.44 | H97: =H90+H93 -> 107095.2 | I97: =I90+I93 -> 88911.4 | J97: =J90+J93 -> 204831.93 | K97: =K90+K93 -> 89198.718
A98: خالص باقی مانده بعد از هزینه های جاری زندگی در هر ماه | C98: =C96-C74 -> 5525.773 | D98: =D96-D74 -> 5829.7977 | E98: =E96-E74 -> 6161.37 | F98: =F96-F74 -> 5865.5435 | G98: =G96-G74 -> 5826.5883 | H98: =H96-H74 -> 4511.505 | I98: =I96-I74 -> 4896.0783 | J98: =J96-J74 -> 11746.642 | K98: =K96-K74 -> 3694.0715
A99: جمع باقی مانده خالص بعد از هزینه های جاری برای یک سال | C99: =C98*12 -> 66309.276 | D99: =D98*12 -> 69957.572 | E99: =E98*12 -> 73936.44 | F99: =F98*12 -> 70386.522 | G99: =G98*12 -> 69919.06 | H99: =H98*12 -> 54138.06 | I99: =I98*12 -> 58752.94 | J99: =J98*12 -> 140959.71 | K99: =K98*12 -> 44328.858
A100: خرید خانه
A101: بدترین حالت بعد از 4 سال (10000 تا در سال کم شده است برای هزینه های اضافی) | C101: =(C87-10000)*4 -> 99542.402 | D101: =(D87-10000)*4 -> 85287.132 | E101: =(E87-10000)*4 -> 105839.44 | F101: =(F87-10000)*4 -> 129785.91 | G101: =(G87-10000)*4 -> 138935.04 | H101: =(H87-10000)*4 -> 94603.44 | I101: =(I87-10000)*4 -> 119519.76 | J101: =(J87-10000)*4 -> 301831.04 | K101: =(K87-10000)*4 -> 116746.48
A102: پس انداز با جمع 4 برابر وام | C102: =C101*5 -> 497712.01 | D102: =D101*5 -> 426435.66 | E102: =E101*5 -> 529197.2 | F102: =F101*5 -> 648929.56 | G102: =G101*5 -> 694675.2 | H102: =H101*5 -> 473017.2 | I102: =I101*5 -> 597598.8 | J102: =J101*5 -> 1509155.2 | K102: =K101*5 -> 583732.39
A103: حدود متراژ با میانگین خانه تک خوابه مرکز شهر(متر مکعب) | C103: =C102/C65 -> 53.081015 | D103: =D102/D65 -> 47.481081 | E103: =E102/E65 -> 170.10244 | F103: =F102/F65 -> 64.43668 | G103: =G102/G65 -> 113.84236 | H103: =H102/H65 -> 28.371017 | I103: =I102/I65 -> 122.1439 | J103: =J102/J65 -> 101.43147 | K103: =K102/K65 -> 71.146791
A104: میانگین بعد از 4 سال (10000 تا در سال کم شده است برای هزینه های اضافی) | C104: =(C99-10000)*4 -> 225237.1 | D104: =(D99-10000)*4 -> 239830.29 | E104: =(E99-10000)*4 -> 255745.76 | F104: =(F99-10000)*4 -> 241546.09 | G104: =(G99-10000)*4 -> 239676.24 | H104: =(H99-10000)*4 -> 176552.24 | I104: =(I99-10000)*4 -> 195011.76 | J104: =(J99-10000)*4 -> 523838.84 | K104: =(K99-10000)*4 -> 137315.43
A105: پس انداز با جمع 4 برابر وام | C105: =C104*5 -> 1126185.5 | D105: =D104*5 -> 1199151.4 | E105: =E104*5 -> 1278728.8 | F105: =F104*5 -> 1207730.4 | G105: =G104*5 -> 1198381.2 | H105: =H104*5 -> 882761.2 | I105: =I104*5 -> 975058.8 | J105: =J104*5 -> 2619194.2 | K105: =K104*5 -> 686577.16
A106: حدود متراژ با میانگین خانه تک خوابه مرکز شهر(متر مکعب) | C106: =C105/C65 -> 120.10775 | D106: =D105/D65 -> 133.5184 | E106: =E105/E65 -> 411.02805 | F106: =F105/F65 -> 119.92386 | G106: =G105/G65 -> 196.38897 | H106: =H105/H65 -> 52.946982 | I106: =I105/I65 -> 199.29338 | J106: =J105/J65 -> 176.03803 | K106: =K105/K65 -> 83.681774

Sheet Works and Salarys
A1: Factors | B1: Iran | C1: Canada | F1: Norway | H1: England | J1: switzerland | K1: Denmark
B2: Tehran | C2: Vancouver | D2: Toronto | E2: Calgary | F2: Oslo | G2: Bergen | H2: London | I2: Birmingham | J2: Zurich | K2: Copenhagen
A3: Software Developer (Full Time)
A4: average (yearly) | B4: 4495 | C4: 108108 | D4: 114412 | E4: 108056 | F4: 104128 | G4: 92160 | H4: 103464 | I4: 74483 | J4: 117842 | K4: 110183
A5: highest paid (yearly) | B5: 7563 | C5: 162957 | D5: 179563 | E5: 163673 | F5: 129025 | G5: 114195 | H5: 158447 | I5: 101568 | J5: 196498 | K5: 136408
A6: loset paid (yearly) | B6: 1944 | C6: 58267 | D6: 54981 | E6: 56411 | F6: 73623 | G6: 65160 | H6: 53763 | I6: 47398 | J6: 83087 | K6: 77835
A7: weekly hour work cap for coworkers | B7: 45 | C7: 40 | D7: 40 | E7: 40 | F7: 37.5 | G7: 37.5 | H7: 40 | I7: 40 | J7: 45 | K7: 37
A8: daily hour work cap for coworkers (Hour) | B8: 9 | C8: 8 | D8: 8 | E8: 8 | F8: 7.5 | G8: 7.5 | H8: 8 | I8: 8 | J8: 9 | K8: 7.5
A9: average per hour | B9: =(B4/12)/(B8*21) -> 1.9819224 | C9: =(C4/12)/(C8*21) -> 53.625 | D9: =(D4/12)/(D8*21) -> 56.751984 | E9: =(E4/12)/(E8*21) -> 53.599206 | F9: =(F4/12)/(F8*21) -> 55.09418 | G9: =(G4/12)/(G8*21) -> 48.761905 | H9: =(H4/12)/(H8*21) -> 51.321429 | I9: =(I4/12)/(I8*21) -> 36.945933 | ... K9: =(K4/12)/(K8*21) -> 58.297884
A10: Description
A11: Childrens PhotoGrapher (Full Time)
A12: average (yearly) | B12: 1253 | C12: 60664 | D12: 59435 | E12: 59464 | F12: 75899 | G12: 68492 | H12: 75028 | I12: 55277 | J12: 99011 | K12: 95344
A13: highest paid (yearly) | B13: 1986 | C13: 74490 | D13: 72981 | E13: 73017 | F13: 93198 | G13: 84103 | H13: 92127 | I13: 67874 | J13: 121238 | K13: 116971
A14: loset paid (yearly) | B14: 827 | C14: 44064 | D14: 43172 | E14: 43193 | F14: 55131 | G14: 49751 | H14: 54497 | I14: 40150 | J14: 71718 | K14: 69194
A15: weekly hour work cap for coworkers | B15: 45 | C15: 40 | D15: 40 | E15: 40 | F15: 37.5 | G15: 37.5 | H15: 40 | I15: 40 | J15: 45 | K15: 37
A16: daily hour work cap for coworkers (Hour) | B16: 9 | C16: 8 | D16: 8 | E16: 8 | F16: 7.5 | G16: 7.5 | H16: 8 | I16: 8 | J16: 9 | K16: 7.5
A17: average per hour | B17: =(B12/12)/(B16*21) -> 0.55246914 | C17: =(C12/12)/(C16*21) -> 30.09127 | D17: =(D12/12)/(D16*21) -> 29.481647 | E17: =(E12/12)/(E16*21) -> 29.496032 | F17: =(F12/12)/(F16*21) -> 40.158201 | G17: =(G12/12)/(G16*21) -> 36.239153 | H17: =(H12/12)/(H16*21) -> 37.21627 | I17: =(I12/12)/(I16*21) -> 27.419147 | ... K17: =(K12/12)/(K16*21) -> 50.446561
A18: Description | C18: حس میکنم برای کانادا رو خیلی کف قیمت نوشتم
A19: Fitness Instructor
A20: average (yearly) | C20: 59205 | D20: 51395 | E20: 52221 | F20: 59899 | G20: 53014 | H20: 47168 | I20: 41101 | J20: 69583 | K20: 64577
A21: highest paid (yearly) | C21: 63262 | D21: 62691 | E21: 63697 | F21: 73063 | G21: 64665 | H21: 52281 | I21: 57401 | J21: 84639 | K21: 78701
A22: loset paid (yearly) | C22: 38200 | D22: 37855 | E22: 38463 | F22: 44118 | G22: 39047 | H22: 32400 | I22: 30301 | J22: 51108 | K22: 47522
A23: weekly hour work cap for coworkers | B23: 45 | C23: 40 | D23: 40 | E23: 40 | F23: 37.5 | G23: 37.5 | H23: 40 | I23: 40 | J23: 45 | K23: 37
A24: daily hour work cap for coworkers (Hour) | B24: 9 | C24: 8 | D24: 8 | E24: 8 | F24: 7.5 | G24: 7.5 | H24: 8 | I24: 8 | J24: 9 | K24: 7.5
A25: average per hour | B25: =(B20/12)/(B24*21) -> 0 | C25: =(C20/12)/(C24*21) -> 29.36756 | D25: =(D20/12)/(D24*21) -> 25.493552 | E25: =(E20/12)/(E24*21) -> 25.903274 | F25: =(F20/12)/(F24*21) -> 31.692593 | G25: =(G20/12)/(G24*21) -> 28.049735 | H25: =(H20/12)/(H24*21) -> 23.396825 | I25: =(I20/12)/(I24*21) -> 20.387401 | ... K25: =(K20/12)/(K24*21) -> 34.167725
A26: Description

Sheet Tax
A1: Country | B1: Country Tax | E1: State | F1: City | G1: State Tax | J1: Sum All Tax | K1: reng tax low to high
B2: Over | C2: Up to | D2: Percentage | G2: Over | H2: Up to | I2: Percentage
A3: Iran | B3: General tax in Iran | E3: All State of Iran | F3: All city of Iran | G3: first | H3: 1135 | I3: 0 | J3: 0
G4: 1135 | H4: 2270 | I4: 0.1 | J4: 0.1
G5: 2270 | H5: 3406 | I5: 0.15 | J5: 0.15
G6: 3406 | H6: 5109 | I6: 0.2 | J6: 0.2
G7: 5109 | H7: 6812 | I7: 0.25 | J7: 0.25
G8: 6812 | H8: 9083 | I8: 0.3 | J8: 0.3
G9: 9083 | H9: more than | I9: 0.35 | J9: 0.35
A10: Canada | B10: Federal bracket tax | E10: British Columbia | F10: Vancouver | G10: first | H10: 33816 | I10: 0.0506 | J10: =D12+I10 -> 0.2006
G11: 33816 | H11: 67633 | I11: 0.077 | J11: =(K11+L11)/2 -> 0.2545 | K11: =D12+I11 -> 0.227 | L11: =D15+I11 -> 0.282
B12: first | C12: 38487 | D12: 0.15 | G12: 67633 | H12: 77651 | I12: 0.105 | J12: =(L12+K12)/2 -> 0.3375 | K12: =D15+I12 -> 0.31 | L12: =D18+I12 -> 0.365
G13: 77651 | H13: 94291 | I13: 0.1229 | J13: =D18+I13 -> 0.3829
G14: 94291 | H14: 127846 | I14: 0.147 | J14: =(L14+K14)/2 -> 0.422 | K14: =D18+I14 -> 0.407 | L14: =D21+I14 -> 0.437
B15: 38487 | C15: 76975 | D15: 0.205 | G15: 127846 | H15: 178299 | I15: 0.168 | J15: =(L15+K15)/2 -> 0.478 | K15: =D21+I15 -> 0.458 | L15: =D24+I15 -> 0.498
G16: 178299 | H16: more than | I16: 0.205 | J16: =D24+I16 -> 0.535
E17: Ontario | F17: Toronto | G17: first | H17: 36294 | I17: 0.0505 | J17: =D12+I17 -> 0.2005
B18: 76975 | C18: 119324 | D18: 0.26 | G18: 36294 | H18: 72589 | I18: 0.0915 | J18: =(K18+L18)/2 -> 0.269 | K18: =D12+I18 -> 0.2415 | L18: =D15+I18 -> 0.2965
G19: 72589 | H19: 117771 | I19: 0.1116 | J19: =(K19+L19)/2 -> 0.3441 | K19: =D15+I19 -> 0.3166 | L19: =D18+I19 -> 0.3716
G20: 117771 | H20: 172731 | I20: 0.1216 | J20: =(K20+L20+M20)/3 -> 0.41493333 | K20: =D18+I20 -> 0.3816 | L20: =D21+I20 -> 0.4116 | M20: =D24+I20 -> 0.4516
B21: 119324 | C21: 169992 | D21: 0.29 | G21: 172731 | H21: more than | I21: 0.1316 | J21: =D24+I21 -> 0.4616
E22: Alberta | F22: Calgary | G22: first | H22: 103026 | I22: 0.1 | J22: =(K22+L22+M22)/3 -> 0.305 | K22: =D12+I22 -> 0.25 | L22: =D15+I22 -> 0.305 | M22: =D18+I22 -> 0.36
G23: 103026 | H23: 123632 | I23: 0.12 | J23: =(K23+L23)/2 -> 0.395 | K23: =D18+I23 -> 0.38 | L23: =D21+I23 -> 0.41
B24: 169992 | C24: more than | D24: 0.33 | G24: 123632 | H24: 164842 | I24: 0.13 | J24: =D21+I24 -> 0.42
G25: 164842 | H25: 247264 | I25: 0.14 | J25: =(K25+L25)/2 -> 0.45 | K25: =D21+I25 -> 0.43 | L25: =D24+I25 -> 0.47
G26: 247264 | H26: more than | I26: 0.15 | J26: =D24+I26 -> 0.48
A27: Norway | B27: The income tax for all jobs and categories | E27: All State of Norway | F27: All City of Norway | G27: 0 | H27: 21277 | I27: 0 | J27: =B29+I27 -> 0.22
G28: 21277 | H28: 29946 | I28: 0.017 | J28: =B29+I28 -> 0.237
B29: 0.22 | G29: 29946 | H29: 71964 | I29: 0.04 | J29: =B29+I29 -> 0.26
G30: 71964 | H30: 108337 | I30: 0.134 | J30: =B29+I30 -> 0.354
G31: 108337 | H31: 223561 | I31: 0.164 | J31: =B29+I31 -> 0.384
G32: 223561 | H32: more than | I32: 0.174 | J32: =B29+I32 -> 0.394
A33: England | B33: General tax in UK | E33: All State of England | F33: All City of England | G33: first | H33: 16873 | I33: 0 | J33: 0
G34: 16873 | H34: 67480 | I34: 0.2 | J34: 0.2
G35: 67480 | H35: 201355 | I35: 0.4 | J35: 0.4
G36: 201355 | H36: more than | I36: 0.45 | J36: 0.45
A37: Switzerland | B37: General tax in Switzerland | E37: All State of Switzerland | F37: All City of Switzerland | G37: 0 | H37: =1.07*30799 -> 32954.93 | I37: 0 | J37: 0
G38: =1.07*30800 -> 32956 | H38: =1.07*50900 -> 54463 | I38: 0.01 | J38: 0.01
G39: =1.07*50901 -> 54464.07 | H39: =1.07*58400 -> 62488 | I39: 0.02 | J39: 0.02
G40: =1.07*58401 -> 62489.07 | H40: =1.07*75300 -> 80571 | I40: 0.03 | J40: 0.03
G41: =1.07*75301 -> 80572.07 | H41: =1.07*90300 -> 96621 | I41: 0.04 | J41: 0.04
G42: =1.07*90301 -> 96622.07 | H42: =1.07*103400 -> 110638 | I42: 0.05 | J42: 0.05
G43: =1.07*103401 -> 110639.07 | H43: =1.07*114700 -> 122729 | I43: 0.06 | J43: 0.06
G44: =1.07*114701 -> 122730.07 | H44: =1.07*124200 -> 132894 | I44: 0.07 | J44: 0.07
G45: =1.07*124201 -> 132895.07 | H45: =1.07*131700 -> 140919 | I45: 0.08 | J45: 0.08
G46: =1.07*131701 -> 140920.07 | H46: =1.07*137300 -> 146911 | I46: 0.09 | J46: 0.09
G47: =1.07*137301 -> 146912.07 | H47: =1.07*141200 -> 151084 | I47: 0.1 | J47: 0.1
G48: =1.07*141201 -> 151085.07 | H48: =1.07*143100 -> 153117 | I48: 0.11 | J48: 0.11
G49: =1.07*143101 -> 153118.07 | H49: =1.07*145000 -> 155150 | I49: 0.12 | J49: 0.12
G50: =1.07*145001 -> 155151.07 | H50: =1.07*895900 -> 958613 | I50: 0.13 | J50: 0.13
G51: =1.07*895901 -> 958614.07 | H51: more than | I51: 0.115 | J51: 0.115
A52: Denmark | B52: General Tax in Denmark | E52: All State of Denmark | F52: All City of Denmark | G52: 0 | H52: 7806 | I52: 0.08 | J52: =I52 -> 0.08 | K52: مالیات دانمارک معتبر نیست از سایت های محاسباتی مالیاتی برای این کشور استفاده کنید
G53: 7806 | H53: 83789 | I53: 0.4283 | J53: =I53 -> 0.4283
G54: 83789 | H54: more than | I54: 0.566 | J54: =I54 -> 0.566

Sheet Society and Population
A1: Country | B1: Immigrant rates in Country | C1: Population in 2020 | D1: Migrants (net) in 2020 | E1: Percentage of Migrants in 2020 | F1: Median age in 2020 | G1: Global Rank in 2020 | H1: Life Expectancy in 2020 | I1: UnEmployment Rate | J1: Description about UnEmployment rate | K1: World Happiness Index | L1: Description World Happiness Index
A3: Iran | B3: -0.0068 | C3: 83992949 | D3: -55000 | E3: =100*(D3/C3) -> -0.065481687 | F3: 32 | G3: 18 | H3: 77.33 | I3: 10.96 | J3: توی ایران زنان خاندار هم شاغل حساب میشن! | K3: 4.672 | L3: این شاخص شامل خانواده، امید به زندگی، آزادی، جنسیت زدگی ، اعتماد، تولید ناخالص داخلی سرانه می باشد و هرچه امتیاز بالاتر باشد کیفیت بالاتری دارد
A4: Canada | B4: 0.21 | C4: 37742154 | D4: 242032 | E4: =100*(D4/C4) -> 0.64127765 | F4: 41.1 | G4: 39 | H4: 82.96 | I4: 0.0948 | K4: 7.232
A5: Norway | B5: 0.185 | C5: 5421241 | D5: 28000 | E5: =100*(D5/C5) -> 0.51648691 | F5: 39.8 | G5: 119 | H5: 82.94 | I5: 0.0462 | K5: 7.488
A6: England | B6: 0.09 | C6: 67886011 | D6: 260650 | E6: =100*(D6/C6) -> 0.38395245 | F6: 40.5 | G6: 21 | H6: 81.77 | I6: 0.041 | K6: 7.06
A7: Switzerland | B7: 0.0455 | C7: 8654622 | D7: 52000 | E7: =100*(D7/C7) -> 0.60083502 | F7: 43.1 | G7: 101 | H7: 84.25 | I7: 0.0494 | K7: 7.56
A8: Denmark | B8: 10.1 | C8: 5792202 | D8: 15200 | E8: =100*(D8/C8) -> 0.26242179 | F8: 42.3 | G8: 115 | H8: 81.4 | I8: 0.056 | K8: 7.646

Sheet Immigrate Ways
A1: Country | B1: Job Offer Visa | E1: Express Entry | F1: Student visa | G1: Skill Worker | H1: Family Sponsership | I1: Provincial nominees | J1: Caregivers | K1: Start-up Visa | L1: Self-employed | M1: Refugees | N1: Buy House | O1: Technology Transfer
B2: Job Seeker | D2: Job Offer
C3: Period Time (Month)
A4: Canada
A5: Norway
A6: England
A7: Switzerland
A8: Denmark
